langak/__init__.py
langak/alphabets.py
langak/detector.py
langak-1.0.0.dist-info/METADATA
langak-1.0.0.dist-info/WHEEL
langak-1.0.0.dist-info/top_level.txt
langak-1.0.0.dist-info/RECORD
