Metadata-Version: 2.4
Name: Langak
Version: 1.0.0
Summary: Simple language detector using alphabets
Author: LongTime
Author-email: noreply@long-time.ru
Classifier: Programming Language :: Python :: 3
Classifier: Topic :: Text Processing :: Linguistic
Requires-Python: >=3.6
Dynamic: author
Dynamic: author-email
Dynamic: classifier
Dynamic: requires-python
Dynamic: summary
